jadex/__init__.py
jadex-0.2.0.dist-info/METADATA
jadex-0.2.0.dist-info/WHEEL
jadex-0.2.0.dist-info/top_level.txt
jadex-0.2.0.dist-info/RECORD
