Metadata-Version: 2.4
Name: jadex
Version: 0.2.0
Summary: JADEX
Author-email: Michael Drolet <michael.drolet@tu-darmstadt.de>
Project-URL: Homepage, https://github.com/mdrolet01/jadex
Classifier: Programming Language :: Python :: 3
Classifier: License :: OSI Approved :: MIT License
Classifier: Operating System :: OS Independent
Requires-Python: >=3.10
Requires-Dist: jax
Requires-Dist: flax
